ackee/__init__.py
ackee/middleware.py
ackee/test_middleware.py
test/__init__.py
test/settings.py
django_ackee_middleware-0.1.1.dist-info/LICENSE
django_ackee_middleware-0.1.1.dist-info/METADATA
django_ackee_middleware-0.1.1.dist-info/WHEEL
django_ackee_middleware-0.1.1.dist-info/top_level.txt
django_ackee_middleware-0.1.1.dist-info/RECORD
