Metadata-Version: 2.1
Name: django-ackee-middleware
Version: 0.1.1
Summary: Django middleware reporting requests to Ackee
Home-page: https://github.com/suda/django-ackee-middleware
Author: Wojtek Siudzinski
Author-email: admin@suda.pl
License: UNKNOWN
Platform: UNKNOWN
Classifier: Programming Language :: Python :: 3
Classifier: License :: OSI Approved :: MIT License
Classifier: Operating System :: OS Independent
Requires-Python: >=3.6
